disp.vhdl
library IEEE;
use IEEE.STD_LOGIC_1164.ALL;
use IEEE.NUMERIC_STD.ALL;

entity disp is 
    port(
        OP: in STD_LOGIC_VECTOR(1 downto 0);
        DIST: in STD_LOGIC;
        CLK: in STD_LOGIC;
        RD1: in STD_LOGIC_VECTOR(7 downto 0);
        SkipVal: in STD_LOGIC_VECTOR(1 downto 0)
    );
end disp;

architecture behav of disp is
    
begin 
    process(OP, DIST,RD1,clk, SkipVal) is
        variable int_val : integer;
        
    begin
    if(rising_edge(CLK)) then
        int_val := to_integer(signed(RD1));
        if((OP = "11") and (DIST = '1')) and (SkipVal = "00") then
            report " " & integer'image(int_val) severity note;
        end if;
    end if;
    end process;
end behav;

jumpsel.vhdl
library ieee;
use ieee.std_logic_1164.all;

entity jumpsel is
port(	
        jcount: in std_logic;
        OP: in std_logic_vector(1 downto 0);
        DIST: in std_logic;
        clk: in std_logic;
        RD1, RD2: in std_logic_vector(7 downto 0);
        O: out std_logic_vector(1 downto 0)
);
end jumpsel;



architecture behav of jumpsel is
    
	signal value: std_logic_vector(1 downto 0) := "00";
    signal feedback: std_logic_vector(1 downto 0) := "00";

begin
   
process (clk, value) 
begin
   if(rising_edge(clk)) then
    O<= feedback;
    value <= feedback;
   end if;
end process;

process(Jcount, OP, DIST, value,RD1, RD2) 
begin
    --if(rising_edge(clk)) then
    if(feedback = "00") then --see if there is a comp instruction
        if(jcount = '1') and (OP = "11") and (DIST = '0') and (RD1 = RD2) then --it is a comp with jump 2
            feedback<= "10";
        
        elsif(jcount = '0') and (OP = "11") and (DIST = '0') and (RD1 = RD2) then --it is a comp with jump 1
            feedback<="01";
        
        else
            feedback<="00";
        end if;
    else --decrement the value
        if(feedback = "10") then
            feedback <= "01";
        elsif(feedback = "01") then
            feedback <= "00";
        end if;    
    end if;
    
    --end if;
end process;
end behav;

decoder.vhdl
library IEEE;
use IEEE.STD_LOGIC_1164.ALL;

entity decoder is
    Port( c: in STD_LOCIG_VECTOR(7 downto 0);
    r1: out STD_LOGIC_VECTOR(1 downto 0);
    r2: out STD_LOGIC_VECTOR(1 downto 0);
    rd: out STD_LOGIC_VECTOR(1 downto 0);
    op: out STD_LOGIC_VECTOR(1 downto 0);
    regw: out STD_LOGIC;
    dist: out STD_LOGIC;
    imm: out STD_LOGIC_VECTOR(3 downto 0);
    jcount: out STD_LOGIC);
end decoder;

architecture behavioral of decoder is

begin
    if (C and "11000000" == "11000000") then --DISP or COMP
        op <= "11";
        dist <= C and "00100000";
        r1 <= C and "00011000";
        if(C and "00100000" == "00000000") then --This is a COMP    
            r2 <= C(2 downto 0); 
            jcount <= C and "00000001" --FIX + REPLACE WITH THE DOWNTO TINGIES
        end if;
    else -- EVERYTHING ELSE
        op <= C and "11000000";
        if(C and "11000000" == "00000000") then --LOAD
            rd <= C and "00110000";
            imm <= C and "00001111";
        else --EVERYTHING ELSE
            rd <= C and "00110000";
            r1 <= C and "00001100";
            r2 <= C and "00000011";
        end if;
    end if;
end behavioral;

fulladder.vhdl
library IEEE;
use IEEE.STD_LOGIC_1164.ALL;

entity fulladder is
 Port ( A : in STD_LOGIC;
 B : in STD_LOGIC;
 Cin : in STD_LOGIC;
 S : out STD_LOGIC;
 Cout : out STD_LOGIC);
end fulladder;

architecture behavioral of fulladder is

begin

 S <= A XOR B XOR Cin ;
 Cout <= (A AND B) OR (Cin AND A) OR (Cin AND B) ;

end behavioral;

addsub.vhdl
library IEEE;
use IEEE.STD_LOGIC_1164.ALL;

entity addsub is
Port ( A : in STD_LOGIC_VECTOR (7 downto 0);
B : in STD_LOGIC_VECTOR (7 downto 0);
Cin : in STD_LOGIC;
subt : in STD_LOGIC;
S : out STD_LOGIC_VECTOR (7 downto 0));
--overflow : out STD_LOGIC);
--Cout : out STD_LOGIC);
end addsub;

architecture Behavioral of addsub is

-- Full Adder VHDL Code Component Decalaration
component fulladder
Port ( A : in STD_LOGIC;
B : in STD_LOGIC;
Cin : in STD_LOGIC;
S : out STD_LOGIC;
Cout : out STD_LOGIC);
end component;

-- Intermediate Carry declaration
signal c1,c2,c3,c4,c5,c6,c7,c8: STD_LOGIC;
signal xor0, xor1, xor2, xor3,xor4,xor5,xor6,xor7: STD_LOGIC;
signal cout: STD_LOGIC;
begin
xor0 <= B(0) xor subt; 
xor1 <= B(1) xor subt;
xor2 <= B(2) xor subt;
xor3 <= B(3) xor subt;
xor4 <= B(4) xor subt; 
xor5 <= B(5) xor subt;
xor6 <= B(6) xor subt;
xor7 <= B(7) xor subt;
cout<='0';
-- Port Mapping Full Adder 4 times
FA1: fulladder port map( A(0), xor0, subt, S(0), c1); --S0
FA2: fulladder port map( A(1), xor1, c1, S(1), c2); --S1
FA3: fulladder port map( A(2), xor2, c2, S(2), c3); --S2
FA4: fulladder port map( A(3), xor3, c3, S(3), c4); --S3
FA5: fulladder port map( A(4), xor4, c4, S(4), c5); --S4
FA6: fulladder port map( A(5), xor5, c5, S(5), c6); --S5
FA7: fulladder port map( A(6), xor6, c6, S(6), c7); --S6
FA8: fulladder port map( A(7), xor7, c7, S(7), Cout); --S7
--overflow <= c7 XOR c8;
--Cout <= c8;
end Behavioral;

alu.vhdl
library ieee;
use ieee.std_logic_1164.all;

entity alu is
    port(
        OP: in STD_LOGIC_VECTOR(1 downto 0);
        RD1: in STD_LOGIC_VECTOR(7 downto 0);
        RD2: in STD_LOGIC_VECTOR(7 downto 0);
        RD: out STD_LOGIC_VECTOR(7 downto 0);
        extend: out STD_LOGIC
);
end alu;

architecture behav of alu is
component addsub
Port ( A : in STD_LOGIC_VECTOR (7 downto 0);
B : in STD_LOGIC_VECTOR (7 downto 0);
Cin : in STD_LOGIC;
subt : in STD_LOGIC;
S : out STD_LOGIC_VECTOR (7 downto 0);
overflow : out STD_LOGIC;
Cout : out STD_LOGIC);
end component;

signal addorsub: STD_LOGIC; --maps directly to subt
--signal extend: STD_LOGIC; --passthrough value of RD1
--signal in1: STD_LOGIC(7 downto 0);
--signal in2: STD_LOGIC(7 downto 0);
signal cin: STD_LOGIC;

begin
    process(OP, RD1, RD2) is
    begin
    if(OP = "01") then
        addorsub<='0'; --add
    elsif(OP = "10") then
        addorsub<='1'; --sub
    else
        addorsub<='0'; --don't care, bypass ALU
    end if;
    cin<='0';
    end process;

    ALU1:addsub port map(RD1, RD2, cin, addorsub, RD);
    end behav;

reg_8bit.vhdl
library ieee;
use ieee.std_logic_1164.all;

entity reg_8bit is
port(	I:	in std_logic_vector (7 downto 0); -- for loading
        clock:		in std_logic; -- positive level triggering in problem 3
        enable: in std_logic;
		O:	out std_logic_vector(7 downto 0) -- output the current register content
);
end reg_8bit;


architecture behav of reg_8bit is
signal temp: std_logic_vector(7 downto 0);

begin
process(I,clock,enable)
begin
if(rising_edge(clock)) then
	if(enable = '1') then
        temp<= I;
        O<=I;
		end if;
    if(enable = '0') then
        temp<=temp;
        O<= temp;
	end if;
end if;
end process;
end behav;

myregister.vhdl
library ieee;
use ieee.std_logic_1164.all;

entity myregister is
port(	
		R1: in std_logic_vector(1 downto 0); 
		R2: in std_logic_vector(1 downto 0);
		OP: in std_logic_vector(1 downto 0);
		DIST: in std_logic;
		CLK: in std_logic; 
		WR: in std_logic_vector(7 downto 0); 
		REG_WRITE: in std_logic;
		RD: in std_logic_vector(1 downto 0);
		RD1: out std_logic_vector(7 downto 0); 
		RD2:	out std_logic_vector(7 downto 0) 
);
end myregister;



architecture behav of myregister is
    component reg_8bit
    port(	I:	in std_logic_vector (7 downto 0); -- for loading
        clock:		in std_logic; -- positive level triggering in problem 3
        enable: in std_logic;
		O:	out std_logic_vector(7 downto 0) -- output the current register content
        );
    end component;
    signal regout1: std_logic_vector(7 downto 0);
	signal regout2: std_logic_vector(7 downto 0);
	signal regout3: std_logic_vector(7 downto 0);
	signal regout4: std_logic_vector(7 downto 0);

	signal regenable1: std_logic;
	signal regenable2: std_logic;
	signal regenable3: std_logic;
    signal regenable4: std_logic;
    

begin
    reg1: reg_8bit port map(wr,clk,regenable1,regout1);
    reg2: reg_8bit port map(wr,clk,regenable2,regout2);
    reg3: reg_8bit port map(wr,clk,regenable3,regout3);
    reg4: reg_8bit port map(wr,clk,regenable4,regout4);
process(CLK)
begin
	
if(rising_edge(clk)) then

	--Handle setup for writing to register
--------------------------------------------------
	if(RD = "00") then
		if(REG_WRITE = '1') then
            regenable1 <= '1';
        end if;
        if(REG_WRITE = '0') then
			regenable1 <= '0';
		end if;
		regenable2 <= '0';
		regenable3 <= '0';
		regenable4 <= '0';
	end if;

	if(RD = "01") then
		if(REG_WRITE = '1') then
			regenable2 <= '1';
		else
			regenable2 <= '0';
		end if;
		regenable1 <= '0';
		regenable3 <= '0';
		regenable4 <= '0';
	end if;

	if(RD = "10") then
		if(REG_WRITE = '1') then
			regenable3 <= '1';
		else
			regenable3 <= '0';
		end if;
		regenable1 <= '0';
		regenable2 <= '0';
		regenable4 <= '0';
	end if;

	if(RD = "11") then
		if(REG_WRITE = '1') then
			regenable4 <= '1';
		else
			regenable4 <= '0';
		end if;
		regenable1 <= '0';
		regenable2 <= '0';
		regenable3 <= '0';
	end if;

--------------------------------------------------------
--Handle demuxing outputs of flipflops to the outputs
	if(OP = "01" or OP = "10" or OP = "00") then --add,load,or sub instruction
		if(R1 = "00") then
			RD1 <= regout1;
		end if;
		if(R1 = "01") then
			RD1 <= regout2;
		end if;
		if(R1 = "10") then
			RD1 <= regout3;
		end if;
		if(R1 = "11") then
			RD1 <= regout4;
		end if;

		if(R2 = "00") then
			RD2 <= regout1;
		end if;
		if(R2 = "01") then
			RD2 <= regout2;
		end if;
		if(R2 = "10") then
			RD2 <= regout3;
		end if;
		if(R2 = "11") then
			RD2 <= regout4;
		end if;

	end if;
	if(OP = "11") then -- COMP or DISP instruction
		if(R1 = "00") then
			RD1 <= regout1;
		end if;
		if(R1 = "01") then
			RD1 <= regout2;
		end if;
		if(R1 = "10") then
			RD1 <= regout3;
		end if;
		if(R1 = "11") then
			RD1 <= regout4;
		end if;
		RD2 <= "00000000";
	end if;
	
end if;
end process;
end behav;

bigcalc.vhdl
library IEEE;
use IEEE.STD_LOGIC_1164.ALL;

entity bigcalc is
    port(	
        I: in std_logic_vector(7 downto 0);
        CLK: in std_logic
    );
end bigcalc;

architecture behav of bigcalc is

    component myregister
    port(	
		R1: in std_logic_vector(1 downto 0); 
		R2: in std_logic_vector(1 downto 0);
		OP: in std_logic_vector(1 downto 0);
		DIST: in std_logic;
		CLK: in std_logic; 
		WR: in std_logic_vector(7 downto 0); 
		REG_WRITE: in std_logic;
		RD: in std_logic_vector(1 downto 0);
		RD1: out std_logic_vector(7 downto 0); 
        RD2:	out std_logic_vector(7 downto 0)
    );
    end component;

    component alu
    port(
        OP: in STD_LOGIC_VECTOR(1 downto 0);
        RD1: in STD_LOGIC_VECTOR(7 downto 0);
        RD2: in STD_LOGIC_VECTOR(7 downto 0);
        RD: out STD_LOGIC_VECTOR(7 downto 0)
    );
    end component;

    component decoder
    port( 
        c: in STD_LOGIC_VECTOR(7 downto 0);
        r1: out STD_LOGIC_VECTOR(1 downto 0);
        r2: out STD_LOGIC_VECTOR(1 downto 0);
        rd: out STD_LOGIC_VECTOR(1 downto 0);
        op: out STD_LOGIC_VECTOR(1 downto 0);
        regw: out STD_LOGIC;
        dist: out STD_LOGIC;
        imm: out STD_LOGIC_VECTOR(3 downto 0);
        jcount: out STD_LOGIC
    );
    end component;

    component jumpsel is
    port(	
        jcount: in std_logic;
        OP: in std_logic_vector(1 downto 0);
        DIST: in std_logic;
        clk: in std_logic;
        RD1, RD2: in std_logic_vector(7 downto 0);
        O: out std_logic_vector(1 downto 0)
    );
    end component;

    component disp is 
    port(
        OP: in STD_LOGIC_VECTOR(1 downto 0);
        DIST: in STD_LOGIC;
        CLK: in STD_LOGIC;
        RD1: in STD_LOGIC_VECTOR(7 downto 0)
    );
    end component;

    signal R1,R2,RD, OP: std_logic_vector(1 downto 0);    
    signal DIST, REG_WRITE,Jcount: std_logic;
    signal WR, RD1,RD2:std_logic_vector(7 downto 0);
    signal imm:std_logic_vector(3 downto 0);
    signal internalJump: std_logic_vector(1 downto 0);
    signal internalRegWr: std_logic;
    signal internalALU: std_logic_vector(7 downto 0);

    begin
    myreg: myregister port map(R1,R2,OP,DIST,CLK,WR,REG_WRITE,RD,RD1,RD2);
    myalu: alu port map(OP,RD1,RD2,internalALU);
    mydecoder: decoder port map(I,R1,R2,Rd,OP,internalRegWr,DIST,IMM,JCOUNT);
    myjumpsel: jumpsel port map(jcount,OP,DIST,clk,RD1,RD2,internalJump); 
    mydist: disp port map(OP, DIST, clk, RD1);
    --handle the mux between ALU and WR
    process(internalALU, imm, OP) is
        begin
        if(OP = "00") then --it is a load
            WR(3 downto 0) <= imm;
            if(imm(3) = '1') then
                WR(7 downto 4) <= "1111";
            else
                WR(7 downto 4) <= "0000";
            end if;
        else
            WR <= internalALU;
        end if;

    end process;

    --handle the black box between jumpsel and regwr
    process(internalJump, internalRegWr) is
        begin
        if(internalJump = "01") or (internalJump = "10") then
            REG_WRITE <= '0';
        else
            REG_WRITE <= internalRegWr;
        end if;
    end process;



end behav;

bigcalc_tb.vhdl
library ieee;
use ieee.std_logic_1164.all;

entity bigcalc_tb is
end bigcalc_tb;

architecture behav of bigcalc_tb is

component bigcalc
port(
    I: in std_logic_vector(7 downto 0);
    CLK: in std_logic
);
end component;

signal i: std_logic_vector(7 downto 0);
signal clk: std_logic;
begin

bigcalc1: bigcalc port map (i, clk);

process
type pattern_type is record

i: std_logic_vector(7 downto 0);
clk: std_logic;

end record;

type pattern_array is array (natural range <>) of pattern_type;
constant patterns : pattern_array :=
--Numerical tests that involve skips
(("00000111", '0'), 
("00000111", '1'), --load $r0 7
("00010111", '0'), 
("00010111", '1'), --load $r1 7
("01000001", '0'),
("01000001", '1'), --add $r0 $r0 $r1
("11100000", '0'),
("11100000", '1'), --display $r0 14
("00000111", '0'), 
("00000111", '1'), --load $r0 7
("11000011", '0'),
("11000011", '1'), --skip 2
("00010001", '0'),
("00010001", '1'), --load $r1 1 SKIPPED
("01000110", '0'),
("01000110", '1'), --add $r0 $r1 $r0 SKIPPED
("11000010", '0'),
("11000010", '1'), -- skip 1
("01000101", '0'),
("01000101", '1'), --add $r0 $r0 $r1 SKIPPED
("01000101", '0'),
("01000101", '1'), --add $r0 $r0 $r1 = 14
("11100000", '0'),
("11100000", '1'), --display final value of $r0: 14.
("00000111", '0'),
("00000111", '1'), --load $r0 7
("11100000", '0'),
("11100000", '1'), --display r0 - 7
("11101000", '0'),
("11101000", '1'), --display r1 - 7
("11000010", '0'),
("11000010", '1'), --skip 1 since r0 and r1 are 7
("00000000", '0'),
("00000000", '1'), --load r0 to 0 SKIPPED
("11100000", '0'),
("11100000", '1'), --display final value of r0 7
("11000010", '0'),
("11000010", '1'), --skip 1 since r0 and r1 are 7
("11100000", '0'),
("11100000", '1'), --display final value of r0 7 SKIPPED
------More Numerical Tests including negative values
("00000111", '0'),
("00000111", '1'), --load $r0 7
("00010111", '0'),
("00010111", '1'), --load $r1 7
("01100001", '0'),
("01100001", '1'), --add $r2 $r0 $r1
("00010001", '0'),
("00010001", '1'), --load $r1 1
("01000110", '0'),
("01000110", '1'), --add $r0 $r1 $r2
("00000000", '0'),
("11100000", '1'), --display final value of $r0: 15.
--An example of how we would fight overflow by subtracting positive numbers instead
--of adding negative numbers which would cause an overflow.
("00011100", '0'),
("00011100", '1'), --load $r1 -4
("00101000", '0'),
("00101000", '1'), --load $r2 -8
("01111001", '0'),
("01111001", '1'), --add $r3 $r2 $r1 , $r3 = -8 +-4 = -12
("00001001", '0'),
("00001001", '1'), --load $r0 -7
("01010011", '0'),
("01010011", '1'), --add $r1 $r0 $r3, $r1 = -7 +-12 = -19
("11101000", '0'),
("11101000", '1'), --display final value: -19
("00000111", '0'),
("00000111", '1'), -- load $r0 7
("00010011", '0'),
("00010011", '1'), -- load $r1 3
("10100001", '0'),
("10100001", '1'), -- sub $r2 $r0 $r1
("11110000", '0'),
("11110000", '1'), --display final value of $r2 - 4
("00100000", '0'), 
("00100000", '1'),--load $r2 0
("00001000", '0'), 
("00001000", '1'),--load $r0 -8
("00011000", '0'), 
("00011000", '1'),--load $r1 -8
("01100001", '0'), 
("01100001", '1'),--add $r2 $r1 $r0 = -8+-8=-16
("01111001", '0'),
("01111001", '1'),--add $r3 $r2 $r0 = -8+-16=-24
("01011011", '0'),
("01011011", '1'),--add $r1 $r2 $r3 = -24+-16=-40
("11101000", '0'),
("11101000", '1') --disp $r3 = -32
);


begin

for n in patterns'range loop
i<=patterns(n).i;
wait for 0 ns;
clk<=patterns(n).clk;
wait for 1 ns;

end loop;
assert false report "end of test" severity note;
wait;
end process;
end behav;

bigcalc.vcd
$date
  Thu May  2 16:58:31 2019
$end
$version
  GHDL v0
$end
$timescale
  1 fs
$end
$scope module standard $end
$upscope $end
$scope module std_logic_1164 $end
$upscope $end
$scope module numeric_std $end
$upscope $end
$scope module bigcalc_tb $end
$var reg 8 ! i[7:0] $end
$var reg 1 " clk $end
$scope module bigcalc1 $end
$var reg 8 # i[7:0] $end
$var reg 1 $ clk $end
$var reg 2 % r1[1:0] $end
$var reg 2 & r2[1:0] $end
$var reg 2 ' rd[1:0] $end
$var reg 2 ( op[1:0] $end
$var reg 1 ) dist $end
$var reg 1 * reg_write $end
$var reg 1 + jcount $end
$var reg 8 , wr[7:0] $end
$var reg 8 - rd1[7:0] $end
$var reg 8 . rd2[7:0] $end
$var reg 4 / imm[3:0] $end
$var reg 2 0 internaljump[1:0] $end
$var reg 1 1 internalregwr $end
$var reg 8 2 internalalu[7:0] $end
$scope module myreg $end
$var reg 2 3 r1[1:0] $end
$var reg 2 4 r2[1:0] $end
$var reg 2 5 op[1:0] $end
$var reg 1 6 dist $end
$var reg 1 7 clk $end
$var reg 8 8 wr[7:0] $end
$var reg 1 9 reg_write $end
$var reg 2 : rd[1:0] $end
$var reg 8 ; rd1[7:0] $end
$var reg 8 < rd2[7:0] $end
$var reg 8 = regout1[7:0] $end
$var reg 8 > regout2[7:0] $end
$var reg 8 ? regout3[7:0] $end
$var reg 8 @ regout4[7:0] $end
$var reg 1 A regenable1 $end
$var reg 1 B regenable2 $end
$var reg 1 C regenable3 $end
$var reg 1 D regenable4 $end
$scope module reg1 $end
$var reg 8 E i[7:0] $end
$var reg 1 F clock $end
$var reg 1 G enable $end
$var reg 8 H o[7:0] $end
$var reg 8 I temp[7:0] $end
$upscope $end
$scope module reg2 $end
$var reg 8 J i[7:0] $end
$var reg 1 K clock $end
$var reg 1 L enable $end
$var reg 8 M o[7:0] $end
$var reg 8 N temp[7:0] $end
$upscope $end
$scope module reg3 $end
$var reg 8 O i[7:0] $end
$var reg 1 P clock $end
$var reg 1 Q enable $end
$var reg 8 R o[7:0] $end
$var reg 8 S temp[7:0] $end
$upscope $end
$scope module reg4 $end
$var reg 8 T i[7:0] $end
$var reg 1 U clock $end
$var reg 1 V enable $end
$var reg 8 W o[7:0] $end
$var reg 8 X temp[7:0] $end
$upscope $end
$upscope $end
$scope module myalu $end
$var reg 2 Y op[1:0] $end
$var reg 8 Z rd1[7:0] $end
$var reg 8 [ rd2[7:0] $end
$var reg 8 \ rd[7:0] $end
$var reg 1 ] addorsub $end
$var reg 1 ^ cin $end
$scope module alu1 $end
$var reg 8 _ a[7:0] $end
$var reg 8 ` b[7:0] $end
$var reg 1 a cin $end
$var reg 1 b subt $end
$var reg 8 c s[7:0] $end
$var reg 1 d c1 $end
$var reg 1 e c2 $end
$var reg 1 f c3 $end
$var reg 1 g c4 $end
$var reg 1 h c5 $end
$var reg 1 i c6 $end
$var reg 1 j c7 $end
$var reg 1 k c8 $end
$var reg 1 l xor0 $end
$var reg 1 m xor1 $end
$var reg 1 n xor2 $end
$var reg 1 o xor3 $end
$var reg 1 p xor4 $end
$var reg 1 q xor5 $end
$var reg 1 r xor6 $end
$var reg 1 s xor7 $end
$var reg 1 t cout $end
$scope module fa1 $end
$var reg 1 u a $end
$var reg 1 v b $end
$var reg 1 w cin $end
$var reg 1 x s $end
$var reg 1 y cout $end
$upscope $end
$scope module fa2 $end
$var reg 1 z a $end
$var reg 1 { b $end
$var reg 1 | cin $end
$var reg 1 } s $end
$var reg 1 !" cout $end
$upscope $end
$scope module fa3 $end
$var reg 1 "" a $end
$var reg 1 #" b $end
$var reg 1 $" cin $end
$var reg 1 %" s $end
$var reg 1 &" cout $end
$upscope $end
$scope module fa4 $end
$var reg 1 '" a $end
$var reg 1 (" b $end
$var reg 1 )" cin $end
$var reg 1 *" s $end
$var reg 1 +" cout $end
$upscope $end
$scope module fa5 $end
$var reg 1 ," a $end
$var reg 1 -" b $end
$var reg 1 ." cin $end
$var reg 1 /" s $end
$var reg 1 0" cout $end
$upscope $end
$scope module fa6 $end
$var reg 1 1" a $end
$var reg 1 2" b $end
$var reg 1 3" cin $end
$var reg 1 4" s $end
$var reg 1 5" cout $end
$upscope $end
$scope module fa7 $end
$var reg 1 6" a $end
$var reg 1 7" b $end
$var reg 1 8" cin $end
$var reg 1 9" s $end
$var reg 1 :" cout $end
$upscope $end
$scope module fa8 $end
$var reg 1 ;" a $end
$var reg 1 <" b $end
$var reg 1 =" cin $end
$var reg 1 >" s $end
$var reg 1 ?" cout $end
$upscope $end
$upscope $end
$upscope $end
$scope module mydecoder $end
$var reg 8 @" c[7:0] $end
$var reg 2 A" r1[1:0] $end
$var reg 2 B" r2[1:0] $end
$var reg 2 C" rd[1:0] $end
$var reg 2 D" op[1:0] $end
$var reg 1 E" regw $end
$var reg 1 F" dist $end
$var reg 4 G" imm[3:0] $end
$var reg 1 H" jcount $end
$upscope $end
$scope module myjumpsel $end
$var reg 1 I" jcount $end
$var reg 2 J" op[1:0] $end
$var reg 1 K" dist $end
$var reg 1 L" clk $end
$var reg 8 M" rd1[7:0] $end
$var reg 8 N" rd2[7:0] $end
$var reg 2 O" o[1:0] $end
$var reg 2 P" feedback[1:0] $end
$var reg 2 Q" value[1:0] $end
$upscope $end
$scope module mydist $end
$var reg 2 R" op[1:0] $end
$var reg 1 S" dist $end
$var reg 1 T" clk $end
$var reg 8 U" rd1[7:0] $end
$var reg 2 V" skipval[1:0] $end
$upscope $end
$upscope $end
$upscope $end
$enddefinitions $end
#0
b00000111 !
0"
b00000111 #
0$
b00 %
b00 &
b00 '
b00 (
0)
1*
0+
b00000111 ,
bUUUUUUUU -
bUUUUUUUU .
b0111 /
bUU 0
11
bUUUUUUUU 2
b00 3
b00 4
b00 5
06
07
b00000111 8
19
b00 :
bUUUUUUUU ;
bUUUUUUUU <
bUUUUUUUU =
bUUUUUUUU >
bUUUUUUUU ?
bUUUUUUUU @
1A
0B
0C
0D
b00000111 E
0F
1G
bUUUUUUUU H
b00000000 I
b00000111 J
0K
0L
bUUUUUUUU M
b00000000 N
b00000111 O
0P
0Q
bUUUUUUUU R
b00000000 S
b00000111 T
0U
0V
bUUUUUUUU W
b00000000 X
b00 Y
bUUUUUUUU Z
bUUUUUUUU [
bUUUUUUUU \
0]
0^
bUUUUUUUU _
bUUUUUUUU `
0a
0b
bUUUUUUUU c
Ud
Ue
Uf
Ug
Uh
Ui
Uj
Uk
Ul
Um
Un
Uo
Up
Uq
Ur
Us
Ut
Uu
Uv
0w
Ux
Uy
Uz
U{
U|
U}
U!"
U""
U#"
U$"
U%"
U&"
U'"
U("
U)"
U*"
U+"
U,"
U-"
U."
U/"
U0"
U1"
U2"
U3"
U4"
U5"
U6"
U7"
U8"
U9"
U:"
U;"
U<"
U="
U>"
U?"
b00000111 @"
b00 A"
b00 B"
b00 C"
b00 D"
1E"
0F"
b0111 G"
0H"
0I"
b00 J"
0K"
0L"
bUUUUUUUU M"
bUUUUUUUU N"
bUU O"
b00 P"
b00 Q"
b00 R"
0S"
0T"
bUUUUUUUU U"
bUU V"
#1000000
1"
1$
b00000111 -
b00000111 .
b00 0
b00001110 2
17
b00000111 ;
b00000111 <
b00000111 =
b00000000 >
b00000000 ?
b00000000 @
1F
b00000111 H
b00000111 I
1K
b00000000 M
1P
b00000000 R
1U
b00000000 W
b00000111 Z
b00000111 [
b00001110 \
b00000111 _
b00000111 `
b00001110 c
1d
1e
1f
0g
0h
0i
0j
1l
1m
1n
0o
0p
0q
0r
0s
0t
1u
1v
0x
1y
1z
1{
1|
1}
1!"
1""
1#"
1$"
1%"
1&"
0'"
0("
1)"
1*"
0+"
0,"
0-"
0."
0/"
00"
01"
02"
03"
04"
05"
06"
07"
08"
09"
0:"
0;"
0<"
0="
0>"
0?"
1L"
b00000111 M"
b00000111 N"
b00 O"
1T"
b00000111 U"
b00 V"
#2000000
b00010111 !
0"
b00010111 #
0$
b01 '
07
b01 :
0A
1B
0F
0G
0K
1L
0P
0U
b00010111 @"
b01 C"
0L"
0T"
#3000000
1"
1$
17
b00000111 >
1F
1K
b00000111 M
b00000111 N
1P
1U
1L"
1T"
#4000000
b01000001 !
0"
b01000001 #
0$
b01 &
b00 '
b01 (
b00001110 ,
b0000 /
b01 4
b01 5
07
b00001110 8
b00 :
1A
0B
b00001110 E
0F
1G
b00001110 J
0K
0L
b00001110 O
0P
b00001110 T
0U
b01 Y
b01000001 @"
b01 B"
b00 C"
b01 D"
b0000 G"
b01 J"
0L"
b01 R"
0T"
#5000000
1"
1$
b00010101 ,
b00001110 -
b00010101 2
17
b00010101 8
b00001110 ;
b00001110 =
b00010101 E
1F
b00001110 H
b00001110 I
b00010101 J
1K
b00010101 O
1P
b00010101 T
1U
b00001110 Z
b00010101 \
b00001110 _
b00010101 c
0d
1g
0u
1x
0y
0|
0}
1'"
0*"
1+"
1."
1/"
1L"
b00001110 M"
1T"
b00001110 U"
#6000000
b11100000 !
0"
b11100000 #
0$
b00 &
b11 (
1)
0*
b00011100 ,
b00001110 .
01
b00011100 2
b00 4
b11 5
16
07
b00011100 8
09
b00001110 <
0A
b00011100 E
0F
0G
b00011100 J
0K
b00011100 O
0P
b00011100 T
0U
b11 Y
b00001110 [
b00011100 \
b00001110 `
b00011100 c
0l
1o
0v
0x
1("
1*"
b11100000 @"
b00 B"
b11 D"
0E"
1F"
b11 J"
1K"
0L"
b00001110 N"
b11 R"
1S"
0T"
#7000000
1"
1$
17
1F
1K
1P
1U
1L"
1T"
#8000000
b00000111 !
0"
b00000111 #
0$
b00 (
0)
1*
b00000111 ,
b0111 /
11
b00 5
06
07
b00000111 8
19
1A
b00000111 E
0F
1G
b00000111 J
0K
b00000111 O
0P
b00000111 T
0U
b00 Y
b00000111 @"
b00 D"
1E"
0F"
b0111 G"
b00 J"
0K"
0L"
b00 R"
0S"
0T"
#9000000
1"
1$
b00000111 -
b00000111 .
b00001110 2
17
b00000111 ;
b00000111 <
b00000111 =
1F
b00000111 H
b00000111 I
1K
1P
1U
b00000111 Z
b00000111 [
b00001110 \
b00000111 _
b00000111 `
b00001110 c
1d
0g
1l
0o
1u
1v
0x
1y
1|
1}
0'"
0("
1*"
0+"
0."
0/"
1L"
b00000111 M"
b00000111 N"
1T"
b00000111 U"
#10000000
b11000011 !
0"
b11000011 #
0$
b01 &
b11 (
0*
1+
b00001110 ,
b0000 /
01
b01 4
b11 5
07
b00001110 8
09
0A
b00001110 E
0F
0G
b00001110 J
0K
b00001110 O
0P
b00001110 T
0U
b11 Y
b11000011 @"
b01 B"
b11 D"
0E"
b0000 G"
1H"
1I"
b11 J"
0L"
b10 Q"
b11 R"
0T"
#11000000
1"
1$
b10 0
17
1F
1K
1P
1U
1L"
b10 O"
b10 P"
b01 Q"
1T"
b10 V"
#12000000
b00010001 !
0"
b00010001 #
0$
b00 &
b01 '
b00 (
0+
b00000001 ,
b0001 /
11
b00 4
b00 5
07
b00000001 8
b01 :
b00000001 E
0F
b00000001 J
0K
b00000001 O
0P
b00000001 T
0U
b00 Y
b00010001 @"
b00 B"
b01 C"
b00 D"
1E"
b0001 G"
0H"
0I"
b00 J"
0L"
b00 R"
0T"
#13000000
1"
1$
b01 0
17
1F
1K
1P
1U
1L"
b01 O"
b01 P"
b00 Q"
1T"
b01 V"
#14000000
b01000110 !
0"
b01000110 #
0$
b01 %
b10 &
b00 '
b01 (
b00000111 ,
b00000000 .
b0000 /
b00000111 2
b01 3
b10 4
b01 5
07
b00000111 8
b00 :
b00000000 <
b00000111 E
0F
b00000111 J
0K
b00000111 O
0P
b00000111 T
0U
b01 Y
b00000000 [
b00000111 \
b00000000 `
b00000111 c
0d
0e
0f
0l
0m
0n
0v
1x
0y
0{
0|
1}
0!"
0#"
0$"
1%"
0&"
0)"
0*"
b01000110 @"
b01 A"
b10 B"
b00 C"
b01 D"
b0000 G"
b01 J"
0L"
b00000000 N"
b01 R"
0T"
#15000000
1"
1$
1*
b00 0
17
19
1A
1F
1G
1K
1P
1U
1L"
b00 O"
b00 P"
1T"
b00 V"
#16000000
b11000010 !
0"
b11000010 #
0$
b00 %
b01 &
b11 (
0*
b00001110 ,
b00000111 .
01
b00001110 2
b00 3
b01 4
b11 5
07
b00001110 8
09
b00000111 <
0A
b00001110 E
0F
0G
b00001110 J
0K
b00001110 O
0P
b00001110 T
0U
b11 Y
b00000111 [
b00001110 \
b00000111 `
b00001110 c
1d
1e
1f
1l
1m
1n
1v
0x
1y
1{
1|
1}
1!"
1#"
1$"
1%"
1&"
1)"
1*"
b11000010 @"
b00 A"
b01 B"
b11 D"
0E"
b11 J"
0L"
b00000111 N"
b01 Q"
b11 R"
0T"
#17000000
1"
1$
b01 0
17
1F
1K
1P
1U
1L"
b01 O"
b01 P"
b00 Q"
1T"
b01 V"
