disp.vhdl
library IEEE;
use IEEE.STD_LOGIC_1164.ALL;
use IEEE.NUMERIC_STD.ALL;

entity disp is 
    port(
        OP: in STD_LOGIC_VECTOR(1 downto 0);
        DIST: in STD_LOGIC;
        CLK: in STD_LOGIC;
        RD1: in STD_LOGIC_VECTOR(7 downto 0)
    );
end disp;

architecture behav of disp is
    signal shit: std_logic;
begin 
    process(OP, DIST, CLK) is
        variable int_val : integer;
        
    begin
    if(rising_edge(CLK)) then
        int_val := to_integer(signed(RD1));
        if((OP = "11") and (DIST = '1')) then
            report " " & integer'image(int_val) severity note;
        end if;
    end if;
    end process;
end behav;

disp_tb.vhdl
library IEEE;
use IEEE.STD_LOGIC_1164.ALL;
use IEEE.NUMERIC_STD.ALL;

entity disp_tb is
end disp_tb;

architecture behav of disp_tb is

    component disp
    port(
        OP: in STD_LOGIC_VECTOR(1 downto 0);
        DIST: in STD_LOGIC;
        CLK: in STD_LOGIC;
        RD1: in STD_LOGIC_VECTOR(7 downto 0)
    );
    end component;

signal    OP:  STD_LOGIC_VECTOR(1 downto 0);
signal    DIST: STD_LOGIC;
signal    CLK: STD_LOGIC;
signal    RD1: STD_LOGIC_VECTOR(7 downto 0);

begin
    disp1: disp port map (OP,DIST,CLK,RD1);
process 
type pattern_type is record

OP:  STD_LOGIC_VECTOR(1 downto 0);
DIST: STD_LOGIC;
CLK: STD_LOGIC;
RD1:  STD_LOGIC_VECTOR(7 downto 0);
end record;

type pattern_array is array (natural range <>) of pattern_type;
constant patterns : pattern_array :=
(("11",'0','0',"11111111"),
("11",'1','1',"11111111"), -- -1
("11",'0','0',"11111111"),
("11",'1','1',"01001110"), -- 78
("11",'0','0',"11111111"),
("11",'1','1',"10000000"), -- -128
("11",'0','0',"11111111"),
("11",'1','1',"01111111"), -- 127
("11",'0','0',"11111111"));--just print it out
begin

for n in patterns'range loop
OP<=patterns(n).OP;
DIST<=patterns(n).DIST;

RD1<=patterns(n).RD1;
wait for 0 ns;
CLK<=patterns(n).CLK;
wait for 1 ns;
end loop;
assert false report "end of test" severity note;
wait;
end process;
end behav;

disp.vcd
$date
  Tue Apr 30 20:38:04 2019
$end
$version
  GHDL v0
$end
$timescale
  1 fs
$end
$scope module standard $end
$upscope $end
$scope module std_logic_1164 $end
$upscope $end
$scope module numeric_std $end
$upscope $end
$scope module disp_tb $end
$var reg 2 ! op[1:0] $end
$var reg 1 " dist $end
$var reg 1 # clk $end
$var reg 8 $ rd1[7:0] $end
$scope module disp1 $end
$var reg 2 % op[1:0] $end
$var reg 1 & dist $end
$var reg 1 ' clk $end
$var reg 8 ( rd1[7:0] $end
$var reg 1 ) shit $end
$upscope $end
$upscope $end
$enddefinitions $end
#0
b11 !
0"
0#
b11111111 $
b11 %
0&
0'
b11111111 (
U)
#1000000
1"
1#
1&
1'
#2000000
0"
0#
0&
0'
#3000000
1"
1#
b01001110 $
1&
1'
b01001110 (
#4000000
0"
0#
b11111111 $
0&
0'
b11111111 (
#5000000
1"
1#
b10000000 $
1&
1'
b10000000 (
#6000000
0"
0#
b11111111 $
0&
0'
b11111111 (
#7000000
1"
1#
b01111111 $
1&
1'
b01111111 (
#8000000
0"
0#
b11111111 $
0&
0'
b11111111 (
