reg_8bit.vhdl
library ieee;
use ieee.std_logic_1164.all;

entity reg_8bit is
port(	I:	in std_logic_vector (7 downto 0); -- for loading
        clock:		in std_logic; -- positive level triggering in problem 3
        enable: in std_logic;
		O:	out std_logic_vector(7 downto 0) -- output the current register content
);
end reg_8bit;


architecture behav of reg_8bit is
signal temp: std_logic_vector(7 downto 0) := "00000000";

begin
process(clock)
begin
if(rising_edge(clock)) then
	if(enable = '1') then
        temp<= I;
        O<=I;
		
    else
        temp<=temp;
        O<= temp;
	end if;
end if;
end process;
end behav;

myregister.vhdl
library ieee;
use ieee.std_logic_1164.all;

entity myregister is
port(	
		R1: in std_logic_vector(1 downto 0); 
		R2: in std_logic_vector(1 downto 0);
		OP: in std_logic_vector(1 downto 0);
		DIST: in std_logic;
		CLK: in std_logic; 
		WR: in std_logic_vector(7 downto 0); 
		REG_WRITE: in std_logic;
		RD: in std_logic_vector(1 downto 0);
		RD1: out std_logic_vector(7 downto 0); 
		RD2:	out std_logic_vector(7 downto 0) 
);
end myregister;



architecture behav of myregister is
    component reg_8bit
    port(	I:	in std_logic_vector (7 downto 0); -- for loading
        clock:		in std_logic; -- positive level triggering in problem 3
        enable: in std_logic;
		O:	out std_logic_vector(7 downto 0) -- output the current register content
        );
    end component;
    signal regout1: std_logic_vector(7 downto 0);
	signal regout2: std_logic_vector(7 downto 0);
	signal regout3: std_logic_vector(7 downto 0);
	signal regout4: std_logic_vector(7 downto 0);

	signal regenable1: std_logic := '0';
	signal regenable2: std_logic := '0';
	signal regenable3: std_logic := '0';
    signal regenable4: std_logic := '0';
    

begin
    reg1: reg_8bit port map(wr,clk,regenable1,regout1);
    reg2: reg_8bit port map(wr,clk,regenable2,regout2);
    reg3: reg_8bit port map(wr,clk,regenable3,regout3);
    reg4: reg_8bit port map(wr,clk,regenable4,regout4);

    	--Handle setup for writing to register
--------------------------------------------------
process (reg_write, RD)
begin
    if(RD = "00") then
		if(REG_WRITE = '1') then
            regenable1 <= '1';
        end if;
        if(REG_WRITE = '0') then
			regenable1 <= '0';
		end if;
		regenable2 <= '0';
		regenable3 <= '0';
		regenable4 <= '0';
	end if;

	if(RD = "01") then
		if(REG_WRITE = '1') then
			regenable2 <= '1';
		else
			regenable2 <= '0';
		end if;
		regenable1 <= '0';
		regenable3 <= '0';
		regenable4 <= '0';
	end if;

	if(RD = "10") then
		if(REG_WRITE = '1') then
			regenable3 <= '1';
		else
			regenable3 <= '0';
		end if;
		regenable1 <= '0';
		regenable2 <= '0';
		regenable4 <= '0';
	end if;

	if(RD = "11") then
		if(REG_WRITE = '1') then
			regenable4 <= '1';
		else
			regenable4 <= '0';
		end if;
		regenable1 <= '0';
		regenable2 <= '0';
		regenable3 <= '0';
	end if;
end process;

process(OP,R1,R2,regout1,regout2,regout3,regout4)
begin
-------------------------------------------------------
--Handle demuxing outputs of flipflops to the outputs
	if(OP = "01" or OP = "10" or OP = "00") then --add,load,or sub instruction
		if(R1 = "00") then
			RD1 <= regout1;
		end if;
		if(R1 = "01") then
			RD1 <= regout2;
		end if;
		if(R1 = "10") then
			RD1 <= regout3;
		end if;
		if(R1 = "11") then
			RD1 <= regout4;
		end if;

		if(R2 = "00") then
			RD2 <= regout1;
		end if;
		if(R2 = "01") then
			RD2 <= regout2;
		end if;
		if(R2 = "10") then
			RD2 <= regout3;
		end if;
		if(R2 = "11") then
			RD2 <= regout4;
		end if;

	end if;
	if(OP = "11") then -- COMP or DISP instruction
		if(R1 = "00") then
			RD1 <= regout1;
		end if;
		if(R1 = "01") then
			RD1 <= regout2;
		end if;
		if(R1 = "10") then
			RD1 <= regout3;
		end if;
		if(R1 = "11") then
			RD1 <= regout4;
		end if;
		RD2 <= "00000000";
	end if;
	

end process;
end behav;

register_tb.vhdl
library ieee;
use ieee.std_logic_1164.all;

--  A testbench has no ports.
entity register_tb is
end register_tb;

architecture behav of register_tb is
--  Declaration of the component that will be instantiated.
component myregister
port(	
		R1: in std_logic_vector(1 downto 0); 
		R2: in std_logic_vector(1 downto 0);
		OP: in std_logic_vector(1 downto 0);
		DIST: in std_logic;
		CLK: in std_logic; 
		WR: in std_logic_vector(7 downto 0); 
        REG_WRITE: in std_logic;
        RD: in std_logic_vector(1 downto 0);
		RD1: out std_logic_vector(7 downto 0); 
		RD2:	out std_logic_vector(7 downto 0) 
);
end component;
--  Specifies which entity is bound with the component.
-- for shift_reg_0: shift_reg use entity work.shift_reg(rtl);
signal wr,rd1,rd2 : std_logic_vector(7 downto 0);
signal dist, clk, reg_write: std_logic;
signal r1,r2,op,rd : std_logic_vector(1 downto 0);
begin
--  Component instantiation.
register1: myregister port map (r1, r2, op, dist, clk, wr,  reg_write,rd, rd1, rd2);

--  This process does the real job.
process
type pattern_type is record
--  The inputs of the shift_reg.
r1,r2: std_logic_vector (1 downto 0);
op : std_logic_vector(1 downto 0);
dist, clk: std_logic;
WR : std_logic_vector (7 downto 0);
reg_write: std_logic;
RD: std_logic_vector(1 downto 0);
rd1,rd2: std_logic_vector(7 downto 0);

end record;
--  The patterns to apply.
type pattern_array is array (natural range <>) of pattern_type;
constant patterns : pattern_array :=
(("00","00","01",'0','0',"00000000",'0',"00","00000000","00000000"), --clock cycle
("00","00","01",'0','1',"11111111",'1',"00","11111111","00000000"), --load 11111111 into r0
("00","00","01",'0','0',"00000000",'0',"00","11111111","00000000"), --clock cycle
("00","00","01",'0','1',"10101010",'1',"00","10101010","00000000"), --load 11111111 into r0
("00","00","01",'0','0',"00000000",'0',"00","10101010","00000000"), --clock cycle
("00","00","01",'0','1',"00000000",'0',"00","10101010","00000000")); --add instruction that reads r0 and r1
begin
--  Check each pattern.
for n in patterns'range loop
--  Set the inputs.
r1 <= patterns(n).r1;
r2 <= patterns(n).r2;
op <= patterns(n).op;
dist <= patterns(n).dist;

WR <= patterns(n).WR;
reg_write<= patterns(n).reg_write;
RD <= patterns(n).RD;
rd1 <= patterns(n).rd1;
rd2 <= patterns(n).rd2;
--  Wait for the results.
wait for 0.5 ns;
clk <= patterns(n).clk;
wait for 0.5 ns;
--  Check the outputs.
if n /= 0 then --ignore the first pattern since it is used to set clock to low and the output is still undefined
assert rd1 = patterns(n).rd1
report "bad rd1 value" severity error;
assert rd2 = patterns(n).rd2
report "bad rd2 value" severity error;
end if;
end loop;
assert false report "end of test" severity note;
--  Wait forever; this will finish the simulation.
wait;
end process;
end behav;

register.vcd
$date
  Tue Apr 30 14:07:58 2019
$end
$version
  GHDL v0
$end
$timescale
  1 fs
$end
$scope module standard $end
$upscope $end
$scope module std_logic_1164 $end
$upscope $end
$scope module register_tb $end
$var reg 8 ! wr[7:0] $end
$var reg 8 " rd1[7:0] $end
$var reg 8 # rd2[7:0] $end
$var reg 1 $ dist $end
$var reg 1 % clk $end
$var reg 1 & reg_write $end
$var reg 2 ' r1[1:0] $end
$var reg 2 ( r2[1:0] $end
$var reg 2 ) op[1:0] $end
$var reg 2 * rd[1:0] $end
$scope module register1 $end
$var reg 2 + r1[1:0] $end
$var reg 2 , r2[1:0] $end
$var reg 2 - op[1:0] $end
$var reg 1 . dist $end
$var reg 1 / clk $end
$var reg 8 0 wr[7:0] $end
$var reg 1 1 reg_write $end
$var reg 2 2 rd[1:0] $end
$var reg 8 3 rd1[7:0] $end
$var reg 8 4 rd2[7:0] $end
$var reg 8 5 regout1[7:0] $end
$var reg 8 6 regout2[7:0] $end
$var reg 8 7 regout3[7:0] $end
$var reg 8 8 regout4[7:0] $end
$var reg 1 9 regenable1 $end
$var reg 1 : regenable2 $end
$var reg 1 ; regenable3 $end
$var reg 1 < regenable4 $end
$scope module reg1 $end
$var reg 8 = i[7:0] $end
$var reg 1 > clock $end
$var reg 1 ? enable $end
$var reg 8 @ o[7:0] $end
$var reg 8 A temp[7:0] $end
$upscope $end
$scope module reg2 $end
$var reg 8 B i[7:0] $end
$var reg 1 C clock $end
$var reg 1 D enable $end
$var reg 8 E o[7:0] $end
$var reg 8 F temp[7:0] $end
$upscope $end
$scope module reg3 $end
$var reg 8 G i[7:0] $end
$var reg 1 H clock $end
$var reg 1 I enable $end
$var reg 8 J o[7:0] $end
$var reg 8 K temp[7:0] $end
$upscope $end
$scope module reg4 $end
$var reg 8 L i[7:0] $end
$var reg 1 M clock $end
$var reg 1 N enable $end
$var reg 8 O o[7:0] $end
$var reg 8 P temp[7:0] $end
$upscope $end
$upscope $end
$upscope $end
$enddefinitions $end
#0
b00000000 !
bUUUUUUUU "
bUUUUUUUU #
0$
U%
0&
b00 '
b00 (
b01 )
b00 *
b00 +
b00 ,
b01 -
0.
U/
b00000000 0
01
b00 2
bUUUUUUUU 3
bUUUUUUUU 4
bUUUUUUUU 5
bUUUUUUUU 6
bUUUUUUUU 7
bUUUUUUUU 8
09
0:
0;
0<
b00000000 =
U>
0?
bUUUUUUUU @
b00000000 A
b00000000 B
UC
0D
bUUUUUUUU E
b00000000 F
b00000000 G
UH
0I
bUUUUUUUU J
b00000000 K
b00000000 L
UM
0N
bUUUUUUUU O
b00000000 P
#500000
0%
0/
0>
0C
0H
0M
#1000000
b11111111 !
1&
b11111111 0
11
bUUUUUUUU 3
bUUUUUUUU 4
19
b11111111 =
1?
b11111111 B
b11111111 G
b11111111 L
#1500000
b11111111 "
bXXXXXXXX #
1%
1/
b11111111 3
bXXXXXXXX 4
b11111111 5
b00000000 6
b00000000 7
b00000000 8
1>
b11111111 @
b11111111 A
1C
b00000000 E
1H
b00000000 J
1M
b00000000 O
#2000000
b00000000 !
0&
b00000000 0
01
b11111111 3
bXXXXXXXX 4
09
b00000000 =
0?
b00000000 B
b00000000 G
b00000000 L
#2500000
0%
0/
0>
0C
0H
0M
#3000000
b10101010 !
b1X1X1X1X "
1&
b10101010 0
11
b1X1X1X1X 3
bXXXXXXXX 4
19
b10101010 =
1?
b10101010 B
b10101010 G
b10101010 L
#3500000
b10101010 "
bX0X0X0X0 #
1%
1/
b10101010 3
bX0X0X0X0 4
b10101010 5
1>
b10101010 @
b10101010 A
1C
1H
1M
#4000000
b00000000 !
0&
b00000000 0
01
b10101010 3
bX0X0X0X0 4
09
b00000000 =
0?
b00000000 B
b00000000 G
b00000000 L
#4500000
0%
0/
0>
0C
0H
0M
#5000000
b10101010 3
bX0X0X0X0 4
