shift_reg_8bit.vhdl
library ieee;
use ieee.std_logic_1164.all;

entity shift_reg_8bit is
port(	I:	in std_logic_vector (7 downto 0); -- for loading
		I_SHIFT_IN: in std_logic; -- shifted in bit for both left and right
		sel:        in std_logic_vector(1 downto 0); -- 00:hold; 01: shift left; 10: shift right; 11: load
		clock:		in std_logic; -- positive level triggering in problem 3
		enable:		in std_logic; -- 0: don't do anything; 1: shift_reg is enabled
		shiftin: in std_logic_vector(1 downto 0); -- 00: regular load 11: regular load 01: shift left load 10: shift right load
		O:	out std_logic_vector(7 downto 0) -- output the current register content
);
end shift_reg_8bit;


architecture behav of shift_reg_8bit is
signal temp: std_logic_vector(7 downto 0);

begin
process(I,clock,sel,enable,shiftin)
begin
if(rising_edge(clock)) then
	if(enable = '1') then
		if(sel = "00") then
			--HOLD
			temp <= temp;
			O <= temp;
		end if;

		if(sel = "01") then
			--SHIFT LEFT
			
			temp(7 downto 1) <= temp(6 downto 0);
			temp(0) <= I_SHIFT_IN;

			--Output is equal to the new value of temp
			O(7 downto 1) <= temp(6 downto 0);
			O(0) <= I_SHIFT_IN;
			
		end if;

		if(sel = "10") then
			--SHIFT RIGHT
			
			temp(6 downto 0) <= temp (7 downto 1);
			temp(7) <= I_SHIFT_IN;

			--Output is equal to the new value of temp
			O(6 downto 0) <= temp (7 downto 1);
			O(7) <= I_SHIFT_IN;
		end if;

		if(sel = "11") then
		--LOAD
			if(shiftin = "00" or shiftin = "11") then
				temp <= I; --set temp equal to the input to load
				O <= I; 
			end if;
			if(shiftin = "01") then --left shift in
				temp(7 downto 1) <= I(6 downto 0);
				temp(0) <= I_SHIFT_IN;
		
				O(7 downto 1) <= I(6 downto 0);
				O(0) <= I_SHIFT_IN;
			end if;
			if(shiftin = "10") then --right shift in
				temp(6 downto 0) <= I(7 downto 1);
				temp(7) <= I_SHIFT_IN;
			
				O(6 downto 0) <= I(7 downto 1);
				O(7) <= I_SHIFT_IN;
			end if;
		end if;	
	end if;
end if;
end process;
end behav;

Old files/shift_reg_tb_8bit.vhdl
library ieee;
use ieee.std_logic_1164.all;

--  A testbench has no ports.
entity shift_reg_tb_8bit is
end shift_reg_tb_8bit;

architecture behav of shift_reg_tb_8bit is
--  Declaration of the component that will be instantiated.
component shift_reg_8bit
port (	I:	in std_logic_vector (7 downto 0);
		I_SHIFT_IN: in std_logic;
		sel:        in std_logic_vector(1 downto 0); -- 00:hold; 01: shift left; 10: shift right; 11: load
		clock:		in std_logic; 
		enable:		in std_logic;
		shiftin: in std_logic_vector(1 downto 0);
		O:	out std_logic_vector(7 downto 0)
);
end component;
--  Specifies which entity is bound with the component.
-- for shift_reg_0: shift_reg use entity work.shift_reg(rtl);
signal i, o : std_logic_vector(7 downto 0);
signal i_shift_in, clk, enable : std_logic;
signal sel,shiftin : std_logic_vector(1 downto 0);
begin
--  Component instantiation.
shift_reg_0: shift_reg_8bit port map (I => i, I_SHIFT_IN => i_shift_in, sel => sel, clock => clk, enable => enable, shiftin => shiftin, O => o);

--  This process does the real job.
process
type pattern_type is record
--  The inputs of the shift_reg.
i: std_logic_vector (7 downto 0);
i_shift_in, clock, enable: std_logic;
sel,shiftin: std_logic_vector(1 downto 0);
--  The expected outputs of the shift_reg.
o: std_logic_vector (7 downto 0);
end record;
--  The patterns to apply.
type pattern_array is array (natural range <>) of pattern_type;
constant patterns : pattern_array :=
(("00000000", '1', '0', '1', "00", "00", "00000000"),
("01110000", '0', '1', '1', "11", "00", "01110000"), --1st rising edge loading 0001 into the shift reg
("00000000", '1', '0', '1', "11", "00", "01110000"),
("00000000", '0', '1', '1', "01", "00", "11100000"), --2nd rising edge shifting left (shift in 0)
("00000000", '1', '0', '1', "11", "00", "11100000"),
("00000000", '0', '1', '1', "10", "00", "01110000"), --3rd rising edge shifting right (shift in 0)
("00000000", '1', '0', '1', "11", "00", "01110000"),
("00000000", '1', '1', '1', "01", "00", "11100001"), -- 4th rising edge shifting left (shift in 1)
("00000000", '1', '0', '1', "11", "00", "11100001"),
("00000000", '1', '1', '1', "10", "00", "11110000"), --5th rising edge shifting right (shift in 1)
("00000000", '1', '0', '1', "11", "00", "11110000"),
("00100000", '0', '1', '1', "11", "01", "01000000"), --6th rising edge shifting input left (shift in 0)
("00000000", '1', '0', '1', "11", "00", "01000000"),
("00100000", '1', '1', '0', "11", "01", "01000000"), --7th NO ENABLE  rising edge shifting input left (shift in 1)
("00000000", '1', '0', '0', "11", "00", "01000000"),
("00100000", '0', '1', '1', "11", "10", "00010000"), --8th rising edge shifting input right (shift in 0)
("00000000", '1', '0', '1', "11", "00", "00010000"));
begin
--  Check each pattern.
for n in patterns'range loop
--  Set the inputs.
i <= patterns(n).i;
i_shift_in <= patterns(n).i_shift_in;
sel <= patterns(n).sel;
clk <= patterns(n).clock;
enable <= patterns(n).enable;
shiftin <= patterns(n).shiftin;
O <= patterns(n).o;
--  Wait for the results.
wait for 1 ns;
--  Check the outputs.
if n /= 0 then --ignore the first pattern since it is used to set clock to low and the output is still undefined
assert o = patterns(n).o
report "bad output value" severity error;
end if;
end loop;
assert false report "end of test" severity note;
--  Wait forever; this will finish the simulation.
wait;
end process;
end behav;

Old files/shift_reg.vcd
$date
  Thu Mar 28 17:31:51 2019
$end
$version
  GHDL v0
$end
$timescale
  1 fs
$end
$scope module standard $end
$upscope $end
$scope module std_logic_1164 $end
$upscope $end
$scope module shift_reg_tb_8bit $end
$var reg 8 ! i[7:0] $end
$var reg 8 " o[7:0] $end
$var reg 1 # i_shift_in $end
$var reg 1 $ clk $end
$var reg 1 % enable $end
$var reg 2 & sel[1:0] $end
$var reg 2 ' shiftin[1:0] $end
$scope module shift_reg_0 $end
$var reg 8 ( i[7:0] $end
$var reg 1 ) i_shift_in $end
$var reg 2 * sel[1:0] $end
$var reg 1 + clock $end
$var reg 1 , enable $end
$var reg 2 - shiftin[1:0] $end
$var reg 8 . o[7:0] $end
$var reg 8 / temp[7:0] $end
$upscope $end
$upscope $end
$enddefinitions $end
#0
b00000000 !
bUUUUUUUU "
1#
0$
1%
b00 &
b00 '
b00000000 (
1)
b00 *
0+
1,
b00 -
bUUUUUUUU .
bUUUUUUUU /
#1000000
b01110000 !
b01110000 "
0#
1$
b11 &
b01110000 (
0)
b11 *
1+
b01110000 .
b01110000 /
#2000000
b00000000 !
1#
0$
b00000000 (
1)
0+
b01110000 .
#3000000
b11100000 "
0#
1$
b01 &
0)
b01 *
1+
b11100000 .
b11100000 /
#4000000
1#
0$
b11 &
1)
b11 *
0+
b11100000 .
#5000000
b01110000 "
0#
1$
b10 &
0)
b10 *
1+
b01110000 .
b01110000 /
#6000000
1#
0$
b11 &
1)
b11 *
0+
b01110000 .
#7000000
b11100001 "
1$
b01 &
b01 *
1+
b11100001 .
b11100001 /
#8000000
0$
b11 &
b11 *
0+
b11100001 .
#9000000
b11110000 "
1$
b10 &
b10 *
1+
b11110000 .
b11110000 /
#10000000
0$
b11 &
b11 *
0+
b11110000 .
#11000000
b00100000 !
b01000000 "
0#
1$
b01 '
b00100000 (
0)
1+
b01 -
b01000000 .
b01000000 /
#12000000
b00000000 !
1#
0$
b00 '
b00000000 (
1)
0+
b00 -
b01000000 .
#13000000
b00100000 !
1$
0%
b01 '
b00100000 (
1+
0,
b01 -
b01000000 .
#14000000
b00000000 !
0$
b00 '
b00000000 (
0+
b00 -
b01000000 .
#15000000
b00100000 !
b00010000 "
0#
1$
1%
b10 '
b00100000 (
0)
1+
1,
b10 -
b00010000 .
b00010000 /
#16000000
b00000000 !
1#
0$
b00 '
b00000000 (
1)
0+
b00 -
b00010000 .
